{
    "codes": {
        "8762": [
            "G\u00e9tye",
            null
        ]
    },
    "streets": [
        {
            "name": "B\u00e9ke",
            "kind": "t\u00e9r",
            "post_code": 0
        },
        {
            "name": "Cs\u00e1nyi",
            "kind": "utca",
            "post_code": 0
        },
        {
            "name": "Hadnagy",
            "kind": "utca",
            "post_code": 0
        },
        {
            "name": "Hegyi",
            "kind": "utca",
            "post_code": 0
        },
        {
            "name": "Kisfaludy",
            "kind": "utca",
            "post_code": 0
        },
        {
            "name": "Kossuth Lajos",
            "kind": "utca",
            "post_code": 0
        }
    ]
}