{
    "codes": {
        "3842": [
            "Halmaj",
            null
        ]
    },
    "streets": [
        {
            "name": "Dank\u00f3 Pista",
            "kind": "\u00fat",
            "post_code": 0
        },
        {
            "name": "H\u00e1rsfa",
            "kind": "utca",
            "post_code": 0
        },
        {
            "name": "Kinizsi P\u00e1l",
            "kind": "\u00fat",
            "post_code": 0
        },
        {
            "name": "M\u00e1jus 1.",
            "kind": "\u00fat",
            "post_code": 0
        },
        {
            "name": "Szabads\u00e1g",
            "kind": "t\u00e9r",
            "post_code": 0
        },
        {
            "name": "Sz\u00e9chenyi",
            "kind": "\u00fat",
            "post_code": 0
        },
        {
            "name": "Vas\u00fat",
            "kind": "utca",
            "post_code": 0
        },
        {
            "name": "V\u00f6r\u00f6smarty",
            "kind": "\u00fat",
            "post_code": 0
        }
    ]
}