{
    "codes": {
        "3011": [
            "Her\u00e9d",
            null
        ]
    },
    "streets": [
        {
            "name": "Ady Endre",
            "kind": "utca",
            "post_code": 0
        },
        {
            "name": "Arany J\u00e1nos",
            "kind": "utca",
            "post_code": 0
        },
        {
            "name": "\u00c1rp\u00e1d",
            "kind": "utca",
            "post_code": 0
        },
        {
            "name": "Bajcsy Zsilinszky",
            "kind": "utca",
            "post_code": 0
        },
        {
            "name": "B\u00e9ke",
            "kind": "utca",
            "post_code": 0
        },
        {
            "name": "Borsz\u00e9ki",
            "kind": "utca",
            "post_code": 0
        },
        {
            "name": "Csap",
            "kind": "utca",
            "post_code": 0
        },
        {
            "name": "Csillag",
            "kind": "utca",
            "post_code": 0
        },
        {
            "name": "D\u00f3zsa Gy\u00f6rgy",
            "kind": "utca",
            "post_code": 0
        },
        {
            "name": "Dr. Vall\u00f3 Ede",
            "kind": "utca",
            "post_code": 0
        },
        {
            "name": "Hatvani",
            "kind": "\u00fat",
            "post_code": 0
        },
        {
            "name": "Her\u00e9di",
            "kind": "utca",
            "post_code": 0
        },
        {
            "name": "Ifj\u00fas\u00e1gi",
            "kind": "utca",
            "post_code": 0
        },
        {
            "name": "Iskola",
            "kind": "utca",
            "post_code": 0
        },
        {
            "name": "J\u00f3zsef Attila",
            "kind": "utca",
            "post_code": 0
        },
        {
            "name": "K\u00e1polna",
            "kind": "utca",
            "post_code": 0
        },
        {
            "name": "Kar\u00e1csonyi",
            "kind": "utca",
            "post_code": 0
        },
        {
            "name": "Kolozsv\u00e1ri",
            "kind": "utca",
            "post_code": 0
        },
        {
            "name": "Kossuth Lajos",
            "kind": "utca",
            "post_code": 0
        },
        {
            "name": "K\u00f6zt\u00e1rsas\u00e1g",
            "kind": "utca",
            "post_code": 0
        },
        {
            "name": "Pet\u0151fi S\u00e1ndor",
            "kind": "utca",
            "post_code": 0
        },
        {
            "name": "Pusztai",
            "kind": "utca",
            "post_code": 0
        },
        {
            "name": "R\u00e1k\u00f3czi Ferenc",
            "kind": "\u00fat",
            "post_code": 0
        },
        {
            "name": "Sport",
            "kind": "utca",
            "post_code": 0
        },
        {
            "name": "Sz\u0151l\u0151hegy",
            "kind": "utca",
            "post_code": 0
        },
        {
            "name": "Tab\u00e1n",
            "kind": "utca",
            "post_code": 0
        },
        {
            "name": "T\u00e1ncsics Mih\u00e1ly",
            "kind": "utca",
            "post_code": 0
        },
        {
            "name": "Temet\u0151",
            "kind": "utca",
            "post_code": 0
        },
        {
            "name": "V\u00f6r\u00f6smarty Mih\u00e1ly",
            "kind": "t\u00e9r",
            "post_code": 0
        }
    ]
}