{
    "codes": {
        "8097": [
            "Nadap",
            null
        ]
    },
    "streets": [
        {
            "name": "Ak\u00e1cfa",
            "kind": "sor",
            "post_code": 0
        },
        {
            "name": "Barackos",
            "kind": "utca",
            "post_code": 0
        },
        {
            "name": "B\u00e9ke",
            "kind": "utca",
            "post_code": 0
        },
        {
            "name": "Bem",
            "kind": "utca",
            "post_code": 0
        },
        {
            "name": "Halad\u00e1s",
            "kind": "\u00fat",
            "post_code": 0
        },
        {
            "name": "Hegyalja",
            "kind": "\u00fat",
            "post_code": 0
        },
        {
            "name": "Kenderf\u00f6ldi",
            "kind": "\u00fat",
            "post_code": 0
        },
        {
            "name": "R\u00e1k\u00f3czi",
            "kind": "utca",
            "post_code": 0
        },
        {
            "name": "Sukor\u00f3i",
            "kind": "\u00fat",
            "post_code": 0
        },
        {
            "name": "Szabads\u00e1g",
            "kind": "utca",
            "post_code": 0
        },
        {
            "name": "szikla-\u00fat",
            "kind": "",
            "post_code": 0
        },
        {
            "name": "Templom",
            "kind": "k\u00f6z",
            "post_code": 0
        },
        {
            "name": "V\u00f6r\u00f6smarty",
            "kind": "utca",
            "post_code": 0
        },
        {
            "name": "Zeng\u0151",
            "kind": "utca",
            "post_code": 0
        }
    ]
}