{
    "codes": {
        "4064": [
            "Nagyhegyes",
            null
        ]
    },
    "streets": [
        {
            "name": "Ady Endre",
            "kind": "utca",
            "post_code": 0
        },
        {
            "name": "Alkotm\u00e1ny",
            "kind": "utca",
            "post_code": 0
        },
        {
            "name": "Angyalh\u00e1zi",
            "kind": "\u00fat",
            "post_code": 0
        },
        {
            "name": "Bart\u00f3k B\u00e9la",
            "kind": "utca",
            "post_code": 0
        },
        {
            "name": "B\u00e9ke",
            "kind": "\u00fat",
            "post_code": 0
        },
        {
            "name": "Bem J\u00f3zsef",
            "kind": "utca",
            "post_code": 0
        },
        {
            "name": "Bethlen",
            "kind": "utca",
            "post_code": 0
        },
        {
            "name": "Bocskai",
            "kind": "utca",
            "post_code": 0
        },
        {
            "name": "Csokonai",
            "kind": "utca",
            "post_code": 0
        },
        {
            "name": "D\u00f3zsa Gy\u00f6rgy",
            "kind": "utca",
            "post_code": 0
        },
        {
            "name": "Hajnal",
            "kind": "utca",
            "post_code": 0
        },
        {
            "name": "Hunyadi",
            "kind": "utca",
            "post_code": 0
        },
        {
            "name": "Ibolya",
            "kind": "utca",
            "post_code": 0
        },
        {
            "name": "Ipari",
            "kind": "\u00fat",
            "post_code": 0
        },
        {
            "name": "J\u00f3kai",
            "kind": "utca",
            "post_code": 0
        },
        {
            "name": "J\u00f3zsef Attila",
            "kind": "utca",
            "post_code": 0
        },
        {
            "name": "Kiserd\u0151",
            "kind": "\u00fat",
            "post_code": 0
        },
        {
            "name": "Kod\u00e1ly Zolt\u00e1n",
            "kind": "utca",
            "post_code": 0
        },
        {
            "name": "K\u00f6lcsey Ferenc",
            "kind": "utca",
            "post_code": 0
        },
        {
            "name": "Kossuth",
            "kind": "utca",
            "post_code": 0
        },
        {
            "name": "Levendula",
            "kind": "utca",
            "post_code": 0
        },
        {
            "name": "Margar\u00e9ta",
            "kind": "utca",
            "post_code": 0
        },
        {
            "name": "M\u00e1ty\u00e1s kir\u00e1ly",
            "kind": "utca",
            "post_code": 0
        },
        {
            "name": "Micsurin",
            "kind": "utca",
            "post_code": 0
        },
        {
            "name": "M\u00f3ricz Zsigmond",
            "kind": "utca",
            "post_code": 0
        },
        {
            "name": "Nefelejcs",
            "kind": "utca",
            "post_code": 0
        },
        {
            "name": "Nyugati",
            "kind": "utca",
            "post_code": 0
        },
        {
            "name": "Pet\u0151fi",
            "kind": "utca",
            "post_code": 0
        },
        {
            "name": "R\u00e1k\u00f3czi",
            "kind": "utca",
            "post_code": 0
        },
        {
            "name": "R\u00f3zsa",
            "kind": "utca",
            "post_code": 0
        },
        {
            "name": "Sz\u00e9chenyi",
            "kind": "utca",
            "post_code": 0
        },
        {
            "name": "T\u00e1ncsics",
            "kind": "utca",
            "post_code": 0
        },
        {
            "name": "Tulip\u00e1n",
            "kind": "utca",
            "post_code": 0
        },
        {
            "name": "Vasv\u00e1ri P\u00e1l",
            "kind": "utca",
            "post_code": 0
        },
        {
            "name": "Veres P\u00e9ter",
            "kind": "utca",
            "post_code": 0
        },
        {
            "name": "Vir\u00e1g",
            "kind": "utca",
            "post_code": 0
        },
        {
            "name": "Zr\u00ednyi",
            "kind": "utca",
            "post_code": 0
        }
    ]
}