{
    "codes": {
        "4977": [
            "Nagyh\u00f3dos",
            null
        ]
    },
    "streets": [
        {
            "name": "D\u00f3zsa",
            "kind": "utca",
            "post_code": 0
        },
        {
            "name": "Felszabadul\u00e1s",
            "kind": "utca",
            "post_code": 0
        },
        {
            "name": "F\u0151",
            "kind": "utca",
            "post_code": 0
        },
        {
            "name": "Pet\u0151fi",
            "kind": "utca",
            "post_code": 0
        }
    ]
}