{
    "codes": {
        "3034": [
            "Sz\u0171csi",
            null
        ]
    },
    "streets": [
        {
            "name": "Cserk\u00e9sz",
            "kind": "utca",
            "post_code": 0
        },
        {
            "name": "Fecske",
            "kind": "utca",
            "post_code": 0
        },
        {
            "name": "Liliom",
            "kind": "utca",
            "post_code": 0
        },
        {
            "name": "Nefelejcs",
            "kind": "utca",
            "post_code": 0
        },
        {
            "name": "R\u00f3zsa",
            "kind": "utca",
            "post_code": 0
        }
    ]
}