{
    "codes": {
        "8051": [
            "S\u00e1rkeresztes",
            null
        ]
    },
    "streets": [
        {
            "name": "Ady Endre",
            "kind": "utca",
            "post_code": 0
        },
        {
            "name": "Ak\u00e1cos",
            "kind": "\u00fat",
            "post_code": 0
        },
        {
            "name": "Arany J\u00e1nos",
            "kind": "utca",
            "post_code": 0
        },
        {
            "name": "B\u00e9ke",
            "kind": "t\u00e9r",
            "post_code": 0
        },
        {
            "name": "Bem",
            "kind": "utca",
            "post_code": 0
        },
        {
            "name": "Borb\u00e1lai",
            "kind": "\u00fat",
            "post_code": 0
        },
        {
            "name": "D\u00f3zsa Gy\u00f6rgy",
            "kind": "utca",
            "post_code": 0
        },
        {
            "name": "G\u00e9za",
            "kind": "utca",
            "post_code": 0
        },
        {
            "name": "J\u00f3kai",
            "kind": "utca",
            "post_code": 0
        },
        {
            "name": "J\u00f3zsef",
            "kind": "utca",
            "post_code": 0
        },
        {
            "name": "Kis",
            "kind": "k\u00f6z",
            "post_code": 0
        },
        {
            "name": "K\u00f6lcsey",
            "kind": "utca",
            "post_code": 0
        },
        {
            "name": "Kossuth",
            "kind": "utca",
            "post_code": 0
        },
        {
            "name": "M\u00f3ra Ferenc",
            "kind": "utca",
            "post_code": 0
        },
        {
            "name": "Orgona",
            "kind": "utca",
            "post_code": 0
        },
        {
            "name": "Pet\u0151fi",
            "kind": "utca",
            "post_code": 0
        },
        {
            "name": "Radn\u00f3ti",
            "kind": "utca",
            "post_code": 0
        },
        {
            "name": "R\u00e1k\u00f3czi",
            "kind": "utca",
            "post_code": 0
        },
        {
            "name": "S\u00e1rv\u00e1ri",
            "kind": "utca",
            "post_code": 0
        },
        {
            "name": "Sz\u00e9chenyi",
            "kind": "utca",
            "post_code": 0
        }
    ]
}